setup.cfg
setup.py
clitube/__init__.py
clitube/app.py
clitube/model.py
clitube.egg-info/PKG-INFO
clitube.egg-info/SOURCES.txt
clitube.egg-info/dependency_links.txt
clitube.egg-info/requires.txt
clitube.egg-info/top_level.txt
scripts/clitube