Metadata-Version: 1.1
Name: clitube
Version: 0.2.5
Summary: Browse and listen Youtube video soundtrack from your terminal
Home-page: https://github.com/NiZiL/clitube
Author: NiZiL
Author-email: biasutto.t@gmail.com
License: UNKNOWN
Download-URL: https://github.com/NiZiL/clitube/tarball/0.2.5
Keywords: YouTube,CLI
Platform: UNKNOWN
Classifier: Development Status :: 3 - Alpha
Classifier: Environment :: Console :: Curses
Classifier: Intended Audience :: End Users/Desktop
Classifier: License :: OSI Approved :: MIT License
Classifier: Operating System :: POSIX :: Linux
Classifier: Programming Language :: Python :: 3 :: Only
Classifier: Topic :: Multimedia :: Sound/Audio
